aws_library/__init__.py
aws_library/core.py
aws_library-0.1.dist-info/METADATA
aws_library-0.1.dist-info/WHEEL
aws_library-0.1.dist-info/top_level.txt
aws_library-0.1.dist-info/RECORD
